lavender_sscc/__init__.py
lavender_sscc/ccs.txt
lavender_sscc/features_pca.npy
lavender_sscc/main.py
lavender_sscc/top_sccs.csv
lavender_sscc-0.0.9.dist-info/licenses/LICENSE
lavender_sscc-0.0.9.dist-info/METADATA
lavender_sscc-0.0.9.dist-info/WHEEL
lavender_sscc-0.0.9.dist-info/top_level.txt
lavender_sscc-0.0.9.dist-info/RECORD
